CHANGES.txt
CONTRIBUTORS.txt
MANIFEST.in
README.txt
setup.cfg
setup.py
Products/__init__.py
Products.Work.egg-info/PKG-INFO
Products.Work.egg-info/SOURCES.txt
Products.Work.egg-info/dependency_links.txt
Products.Work.egg-info/entry_points.txt
Products.Work.egg-info/namespace_packages.txt
Products.Work.egg-info/not-zip-safe
Products.Work.egg-info/paster_plugins.txt
Products.Work.egg-info/requires.txt
Products.Work.egg-info/top_level.txt
Products/Work/README.txt
Products/Work/__init__.py
Products/Work/config.py
Products/Work/configure.zcml
Products/Work/interfaces.py
Products/Work/setuphandlers.py
Products/Work/tests.py
Products/Work/browser/__init__.py
Products/Work/browser/configure.zcml
Products/Work/browser/work.gif
Products/Work/browser/work.pt
Products/Work/content/__init__.py
Products/Work/content/configure.zcml
Products/Work/content/work.py
Products/Work/portlets/__init__.py
Products/Work/portlets/configure.zcml
Products/Work/profiles/default/browserlayer.xml
Products/Work/profiles/default/diff_tool.xml
Products/Work/profiles/default/factorytool.xml
Products/Work/profiles/default/import_steps.xml
Products/Work/profiles/default/metadata.xml
Products/Work/profiles/default/portlets.xml
Products/Work/profiles/default/rolemap.xml
Products/Work/profiles/default/tinymce.xml
Products/Work/profiles/default/types.xml
Products/Work/profiles/default/types/Work.xml
Products/Work/tests/__init__.py
Products/Work/tests/base.py
Products/Work/tests/doc_tests.py
Products/Work/tests/test_doctest.py
docs/HISTORY.txt
docs/INSTALL.txt
docs/LICENSE.GPL
docs/LICENSE.txt