Metadata-Version: 1.0
Name: Products.Work
Version: 0.0.4
Summary: A representation of a work.
Home-page: http://svn.plone.org/svn/plone/plone.example
Author: Rui Guerra
Author-email: rui AT v2 DOT nl
License: GPL
Platform: UNKNOWN
Classifier: Framework :: Plone
Classifier: Intended Audience :: Developers
Classifier: Topic :: Software Development :: Libraries :: Python Modules
Classifier: License :: OSI Approved :: GNU General Public License (GPL)
